{
  "resources": [
    {
      "path": "data.csv",
      "name": "data",
      "profile": "tabular-data-resource",
      "scheme": "file",
      "format": "csv",
      "hashing": "md5",
      "encoding": "utf-8",
      "schema": {
        "fields": [
          {
            "name": "Year",
            "type": "integer"
          },
          {
            "name": "Region",
            "type": "string",
            "constraints": {
              "enum": [
                "Enzkreis",
                "Land Baden-W체rttemberg",
                ""
              ]
            }
          },
          {
            "name": "Sektor",
            "type": "string",
            "constraints": {
              "enum": [
                "Besch채ftigungsanteil 1. Sektor",
                "Besch채ftigungsanteil 2. Sektor",
                "Besch채ftigungsanteil 3. Sektor",
                ""
              ]
            }
          },
          {
            "name": "Value",
            "type": "number"
          }
        ]
      }
    }
  ],
  "profile": "data-package",
  "name": "9-5-a",
  "title": "9-5-a"
}